Workbook

Sheet Assumptions
A1: Microsoft (MSFT) — AI Capex ROI Model
A2: Simplified DCF & Capex-Efficiency Analysis — data as of Q4 FY2026 (reported July 29, 2026)
A4: Key Assumptions (editable inputs in yellow)
A5: Valuation date | B5: 2026-08-18 | D5: Analysis date
A6: Current share price ($) | B6: 500 | D6: Source: market data, week of Aug 11-18, 2026 (MSFT traded ~$497-507)
A7: Shares outstanding (mm) | B7: 7430 | D7: Source: Q4 FY26 10-Q, diluted shares outstanding
A8: WACC | B8: 0.09 | D8: Assumed: risk-free ~4.2% + beta ~0.9 x ERP ~5.3%; mega-cap low-beta discount rate
A9: Terminal growth rate | B9: 0.035 | D9: Assumed: long-run nominal GDP-like growth
A10: Tax rate (effective, normalized) | B10: 0.19 | D10: Source: MSFT historical effective tax rate ~18-19%
A11: FY26 Revenue ($mm) | B11: 331840 | D11: Source: MSFT FY2026 10-K / Q4 FY26 earnings release, total company revenue
A12: FY26 Operating income ($mm) | B12: 155000 | D12: Source: Q4 FY26 earnings call — FY26 operating income >$155bn, +21% YoY
A13: FY26 Capex + finance leases ($mm) | B13: 115950 | D13: Source: FY26 property & equipment capex, +80% YoY vs FY25 $64.55bn (24/7 Wall St. earnings recap)
A14: FY25 Capex ($mm) | B14: 64550 | D14: Source: FY25 capex per FY26 earnings recap (comparable base)
A15: Capex as % of revenue, FY26 | B15: =B13/B11 -> 0.34941538 | D15: Elevated vs historical ~15-20% norm — this is the core debate the model tests
A16: D&A as % of capex, FY26 (assumed lag) | B16: 0.55 | D16: Assumption: D&A runs ~55% of same-year capex given multi-year useful life (recently extended to 25 yrs on buildings)
A17: Azure/cloud revenue growth, Q4 FY26 (cc) | B17: 0.43 | D17: Source: Q4 FY26 earnings call, Azure revenue growth 43% constant currency
A18: Intelligent Cloud segment revenue, Q4 FY26 ($mm) | B18: 39310 | D18: Source: Q4 FY26 earnings release, Intelligent Cloud segment
A19: Commercial RPO ($mm) | B19: 678000 | D19: Source: Q4 FY26 earnings release, +84% YoY, >2x FY26 revenue
A22: Note on data quality
A23: All figures above are drawn from Microsoft's and Amazon's Q4 FY2026 / Q2 2026 public earnings releases and earnings calls (sources noted per line). Forward projections in the DCF tab are this analyst's assumptions built on top of that reported base, not company guidance beyond the one-quarter forward guide Microsoft gave for Q1 FY27.

Sheet DCF Model
A1: Microsoft — Simplified Unlevered DCF (FY2026A–FY2031E)
A3: ($ in millions)
B4: FY2026A | C4: FY2027E | D4: FY2028E | E4: FY2029E | F4: FY2030E | G4: FY2031E
A5: Revenue growth % (assumption) | C5: 0.15 | D5: 0.13 | E5: 0.11 | F5: 0.09 | G5: 0.07
A6: Revenue | B6: =Assumptions!B11 -> 331840 | C6: =B6*(1+C5) -> 381616 | D6: =C6*(1+D5) -> 431226.08 | E6: =D6*(1+E5) -> 478660.95 | F6: =E6*(1+F5) -> 521740.43 | G6: =F6*(1+G5) -> 558262.26
A8: Operating margin % (assumption) | C8: 0.44 | D8: 0.45 | E8: 0.46 | F8: 0.465 | G8: 0.47
A9: Operating income (EBIT) | B9: =Assumptions!B12 -> 155000 | C9: =C6*C8 -> 167911.04 | D9: =D6*D8 -> 194051.74 | E9: =E6*E8 -> 220184.04 | F9: =F6*F8 -> 242609.3 | G9: =G6*G8 -> 262383.26
A10: Less: Cash taxes | B10: =-B9*Assumptions!$B$10 -> -29450 | C10: =-C9*Assumptions!$B$10 -> -31903.098 | D10: =-D9*Assumptions!$B$10 -> -36869.83 | E10: =-E9*Assumptions!$B$10 -> -41834.967 | F10: =-F9*Assumptions!$B$10 -> -46095.767 | G10: =-G9*Assumptions!$B$10 -> -49852.82
A11: NOPAT (unlevered) | B11: =B9+B10 -> 125550 | C11: =C9+C10 -> 136007.94 | D11: =D9+D10 -> 157181.91 | E11: =E9+E10 -> 178349.07 | F11: =F9+F10 -> 196513.53 | G11: =G9+G10 -> 212530.44
A13: Capex % of revenue (assumption; normalizing from FY26 peak) | C13: 0.3 | D13: 0.26 | E13: 0.23 | F13: 0.21 | G13: 0.2
A14: Capital expenditures | B14: =-Assumptions!B13 -> -115950 | C14: =-C6*C13 -> -114484.8 | D14: =-D6*D13 -> -112118.78 | E14: =-E6*E13 -> -110092.02 | F14: =-F6*F13 -> -109565.49 | G14: =-G6*G13 -> -111652.45
A15: D&A (% of capex, lagged effect) | B15: =-B14*Assumptions!$B$16 -> 63772.5 | C15: =-C14*Assumptions!$B$16 -> 62966.64 | D15: =-D14*Assumptions!$B$16 -> 61665.329 | E15: =-E14*Assumptions!$B$16 -> 60550.61 | F15: =-F14*Assumptions!$B$16 -> 60261.02 | G15: =-G14*Assumptions!$B$16 -> 61408.849
A16: Change in net working capital (assumed ~0) | B16: 0 | C16: 0 | D16: 0 | E16: 0 | F16: 0 | G16: 0
A18: Unlevered Free Cash Flow | B18: =B11+B15+B14+B16 -> 73372.5 | C18: =C11+C15+C14+C16 -> 84489.782 | D18: =D11+D15+D14+D16 -> 106728.45 | E18: =E11+E15+E14+E16 -> 128807.66 | F18: =F11+F15+F14+F16 -> 147209.06 | G18: =G11+G15+G14+G16 -> 162286.84
A20: Discount period | C20: 1 | D20: 2 | E20: 3 | F20: 4 | G20: 5
A21: Discount factor @ WACC | C21: =1/(1+Assumptions!$B$8)^C20 -> 0.91743119 | D21: =1/(1+Assumptions!$B$8)^D20 -> 0.84167999 | E21: =1/(1+Assumptions!$B$8)^E20 -> 0.77218348 | F21: =1/(1+Assumptions!$B$8)^F20 -> 0.70842521 | G21: =1/(1+Assumptions!$B$8)^G20 -> 0.64993139
A22: PV of FCF | C22: =C18*C21 -> 77513.562 | D22: =D18*D21 -> 89831.205 | E22: =E18*E21 -> 99463.148 | F22: =F18*F21 -> 104286.61 | G22: =G18*G21 -> 105475.31
A24: Terminal value (Gordon Growth, at end of FY31E) | G24: =G18*(1+Assumptions!$B$9)/(Assumptions!$B$8-Assumptions!$B$9) -> 3053943.3
A25: PV of terminal value | G25: =G24*G21 -> 1984853.6
A27: Sum of PV of explicit FCF (FY27E-FY31E) | B27: =SUM(C22:G22) -> 476569.84
A28: PV of terminal value | B28: =G25 -> 1984853.6
A29: Enterprise Value | B29: =B27+B28 -> 2461423.4
A31: Implied EV / FY26 EBIT multiple | B31: =B29/Assumptions!B11 -> 7.4175007
A32: % of EV from terminal value | B32: =B28/B29 -> 0.80638445

Sheet Implied Value
A1: Implied Share Price & Sensitivity
A3: Enterprise Value ($mm) | B3: ='DCF Model'!B29 -> 2461423.4
A4: Add: Cash & short-term investments ($mm) | B4: 76800 | C4: Source: Q4 FY26 earnings release, cash + STI as of June 30, 2026
A5: Less: Total debt ($mm) | B5: -31100 | C5: Source: Q4 FY26 earnings release, long-term debt incl. current portion
A6: Equity Value ($mm) | B6: =B3+B4+B5 -> 2507123.4
A8: Shares outstanding (mm) | B8: =Assumptions!B7 -> 7430
A9: Implied share price ($) | B9: =B6/B8 -> 337.43249
A11: Current share price ($) | B11: =Assumptions!B6 -> 500
A12: Implied upside / (downside) | B12: =B9/B11-1 -> -0.32513501
A15: Sensitivity: Implied share price vs. WACC and Terminal Growth
A16: Note: this is a static 2-scenario illustration (base case shown above). A full data table would require Excel's What-If Data Table feature (Ctrl+Alt+F9 iterative calc) which is not reproducible via formula alone here — see the sensitivity chart in the written report for the full WACC x growth grid computed in Python.

Sheet Comps - Cloud Capex
A1: Cloud Capex Efficiency Benchmark — Microsoft (Azure) vs. Amazon (AWS)
A3: Metric (most recent quarter, Q2/Q4 2026) | B3: Microsoft (Azure/Intelligent Cloud) | C3: Amazon (AWS) | D3: Source
A4: Cloud segment revenue ($mm, quarterly) | B4: 39310 | C4: 42200 | D4: MSFT Q4 FY26 & AMZN Q2 2026 earnings releases
A5: Cloud revenue growth YoY | B5: 0.32 | C5: 0.367 | D5: MSFT Intelligent Cloud +32%; AWS +36.7% (both as reported)
A6: Cloud constant-currency growth (Azure only) | B6: 0.43 | C6: n/a | D6: Azure specifically grew 43% cc per MSFT Q4 FY26 call
A7: Cloud operating margin | B7: n/a (segment not fully disclosed) | C7: 0.394 | D7: AWS margin disclosed at 39.4%, up from 32.9% YoY; MSFT does not break out Azure-only margin
A8: Company-wide quarterly capex ($mm) | B8: 41000 | C8: 53100 | D8: MSFT capex+finance leases; AMZN cash capex, both Q2/Q4 2026
A9: Capex YoY growth | B9: 0.69 | C9: ~0.65-0.70 (TTM P&E +64%) | D9: MSFT +69% YoY; AMZN TTM property & equipment +64% YoY
A10: Full-year capex guidance ($bn) | B10: 175 | C10: 220 | D10: MSFT calendar-2026 capex revised to ~$175bn (from ~$190bn); AMZN raised to ~$220bn (from ~$200bn)
A11: Contracted backlog / RPO ($bn) | B11: 678 | C11: 496 | D11: MSFT commercial RPO +84% YoY; AWS backlog growing triple digits
A12: Market capitalization ($tn, approx.) | B12: 3.7 | C12: 2.55 | D12: As of mid-August 2026 market data
A14: Implied capex intensity (company-wide quarterly capex / quarterly total revenue) | B14: =B8/90010 -> 0.45550494 | C14: =C8/200600 -> 0.26470588 | D14: Denominator: MSFT Q4 FY26 total revenue $90.01bn; AMZN Q2 2026 total revenue $200.6bn
